iqrfpy/__init__.py
iqrfpy/async_response.py
iqrfpy/confirmation.py
iqrfpy/exceptions.py
iqrfpy/irequest.py
iqrfpy/iresponse.py
iqrfpy/itransport.py
iqrfpy/messages.py
iqrfpy/py.typed
iqrfpy/response_factory.py
iqrfpy/enums/__init__.py
iqrfpy/enums/commands.py
iqrfpy/enums/message_types.py
iqrfpy/enums/peripherals.py
iqrfpy/enums/py.typed
iqrfpy/ext/__init__.py
iqrfpy/ext/py.typed
iqrfpy/objects/__init__.py
iqrfpy/objects/binaryoutput_state.py
iqrfpy/objects/coordinator_authorize_bond_params.py
iqrfpy/objects/coordinator_dpa_param.py
iqrfpy/objects/exploration_per_enum_data.py
iqrfpy/objects/exploration_per_info_data.py
iqrfpy/objects/frc_params.py
iqrfpy/objects/init_phy_data.py
iqrfpy/objects/io_triplet.py
iqrfpy/objects/node_read_data.py
iqrfpy/objects/node_validate_bonds_params.py
iqrfpy/objects/os_batch_data.py
iqrfpy/objects/os_indicate_param.py
iqrfpy/objects/os_load_code_flags.py
iqrfpy/objects/os_read_data.py
iqrfpy/objects/os_security_type_param.py
iqrfpy/objects/os_sleep_params.py
iqrfpy/objects/os_tr_conf_byte.py
iqrfpy/objects/os_tr_conf_data.py
iqrfpy/objects/sensor_data.py
iqrfpy/objects/sensor_written_data.py
iqrfpy/objects/tr_mcu_type_data.py
iqrfpy/peripherals/__init__.py
iqrfpy/peripherals/py.typed
iqrfpy/peripherals/binaryoutput/__init__.py
iqrfpy/peripherals/binaryoutput/requests/__init__.py
iqrfpy/peripherals/binaryoutput/requests/enumerate.py
iqrfpy/peripherals/binaryoutput/requests/set_output.py
iqrfpy/peripherals/binaryoutput/responses/__init__.py
iqrfpy/peripherals/binaryoutput/responses/enumerate.py
iqrfpy/peripherals/binaryoutput/responses/set_output.py
iqrfpy/peripherals/coordinator/__init__.py
iqrfpy/peripherals/coordinator/requests/__init__.py
iqrfpy/peripherals/coordinator/requests/addr_info.py
iqrfpy/peripherals/coordinator/requests/authorize_bond.py
iqrfpy/peripherals/coordinator/requests/backup.py
iqrfpy/peripherals/coordinator/requests/bond_node.py
iqrfpy/peripherals/coordinator/requests/bonded_devices.py
iqrfpy-0.2.11.dist-info/licenses/LICENSE
iqrfpy-0.2.11.dist-info/METADATA
iqrfpy-0.2.11.dist-info/WHEEL
iqrfpy-0.2.11.dist-info/top_level.txt
iqrfpy-0.2.11.dist-info/RECORD
