Metadata-Version: 2.4
Name: iqrfpy
Version: 0.2.11
Summary: A python library for communication with IQRF Network
Home-page: https://gitlab.iqrf.org/open-source/iqrf-sdk/iqrfpy/iqrfpy
Author: Karel Hanák
Author-email: karel.hanak@iqrf.org
License: Apache-2.0
Project-URL: Changelog, https://apidocs.iqrf.org/iqrfpy/latest/iqrfpy.html#changelog
Project-URL: Documentation, https://apidocs.iqrf.org/iqrfpy/latest/iqrfpy.html
Project-URL: Issues tracker, https://gitlab.iqrf.org/open-source/iqrf-sdk/libiqrf-python/-/issues
Project-URL: Source code, https://gitlab.iqrf.org/open-source/iqrf-sdk/libiqrf-python
Keywords: iqrf,dpa
Classifier: Development Status :: 3 - Alpha
Classifier: License :: OSI Approved :: Apache Software License
Classifier: Programming Language :: Python
Classifier: Programming Language :: Python :: 3
Classifier: Programming Language :: Python :: 3.10
Classifier: Programming Language :: Python :: 3.11
Classifier: Programming Language :: Python :: 3.12
Classifier: Operating System :: Microsoft :: Windows
Classifier: Operating System :: POSIX
Classifier: Operating System :: Unix
Classifier: Operating System :: MacOS
Requires-Python: >=3.10
License-File: LICENSE
Dynamic: license-file
